AxonDeepSeg/__init__.py
AxonDeepSeg/ads_utils.py
AxonDeepSeg/apply_model.py
AxonDeepSeg/download_model.py
AxonDeepSeg/download_tests.py
AxonDeepSeg/integrity_test.py
AxonDeepSeg/logo_ads-alpha.png
AxonDeepSeg/logo_ads-alpha_small.png
AxonDeepSeg/model_cards.py
AxonDeepSeg/params.py
AxonDeepSeg/postprocessing.py
AxonDeepSeg/segment.py
AxonDeepSeg/version.txt
AxonDeepSeg/ads_napari/Settings_menu_ui.ui
AxonDeepSeg/ads_napari/__init__.py
AxonDeepSeg/ads_napari/_widget.py
AxonDeepSeg/ads_napari/napari.yaml
AxonDeepSeg/ads_napari/settings_menu_ui.py
AxonDeepSeg/morphometrics/__init__.py
AxonDeepSeg/morphometrics/aggregate.py
AxonDeepSeg/morphometrics/compute_morphometrics.py
AxonDeepSeg/morphometrics/launch_morphometrics_computation.py
AxonDeepSeg/qa/__init__.py
AxonDeepSeg/qa/custom_matplotlibrc
AxonDeepSeg/qa/generate_report_demo.py
AxonDeepSeg/qa/metrics_qa.py
AxonDeepSeg/qa/report_template.html
AxonDeepSeg/testing/__init__.py
AxonDeepSeg/testing/launch_performance_metrics.py
AxonDeepSeg/testing/segmentation_scoring.py
AxonDeepSeg/visualization/__init__.py
AxonDeepSeg/visualization/colorization.py
AxonDeepSeg/visualization/merge_masks.py
AxonDeepSeg/visualization/simulate_axons.py
axondeepseg-5.3.0.dist-info/licenses/LICENSE
axondeepseg-5.3.0.dist-info/METADATA
axondeepseg-5.3.0.dist-info/WHEEL
axondeepseg-5.3.0.dist-info/entry_points.txt
axondeepseg-5.3.0.dist-info/top_level.txt
axondeepseg-5.3.0.dist-info/RECORD
