Metadata-Version: 2.4
Name: AxonDeepSeg
Version: 5.3.0
Summary: Axon/Myelin segmentation using AI
Author-email: "NeuroPoly Lab, Polytechnique Montreal" <axondeepseg@googlegroups.com>
License: MIT
Project-URL: Homepage, https://github.com/neuropoly/axondeepseg
Project-URL: Bug Tracker, https://github.com/axondeepseg/axondeepseg/issues
Project-URL: Documentation, https://github.com/axondeepseg/axondeepseg#README.md
Project-URL: Source Code, https://github.com/axondeepseg/axondeepseg
Project-URL: User Support, https://github.com/axondeepseg/axondeepseg/issues
Keywords: axon,myelin,segmentation,microscopy
Classifier: Development Status :: 5 - Production/Stable
Classifier: Intended Audience :: Science/Research
Classifier: License :: OSI Approved :: MIT License
Classifier: Framework :: napari
Classifier: Operating System :: OS Independent
Classifier: Programming Language :: Python
Classifier: Programming Language :: Python :: 3
Classifier: Programming Language :: Python :: 3 :: Only
Classifier: Programming Language :: Python :: 3.11
Classifier: Programming Language :: Python :: 3.12
Classifier: Topic :: Scientific/Engineering :: Image Processing
Requires-Python: <3.13,>=3.11
License-File: LICENSE
Requires-Dist: numpy<2
Requires-Dist: scipy
Requires-Dist: scikit-image!=0.25.0,!=0.25.1
Requires-Dist: tabulate
Requires-Dist: pandas
Requires-Dist: matplotlib
Requires-Dist: mpld3
Requires-Dist: tqdm
Requires-Dist: requests
Requires-Dist: pillow!=9.0.0
Requires-Dist: imageio>=2.28.0
Requires-Dist: pytest
Requires-Dist: pytest-cov
Requires-Dist: prettytable
Requires-Dist: jupyter
Requires-Dist: openpyxl
Requires-Dist: qtconsole<5.4.2
Requires-Dist: napari[all]
Requires-Dist: acvl_utils!=0.2.1
Requires-Dist: nnunetv2==2.2.1
Requires-Dist: loguru
Requires-Dist: torch<2.4.0
Requires-Dist: pydicom<3
Requires-Dist: pytest-qt
Requires-Dist: magicgui
Requires-Dist: qtpy
Requires-Dist: jinja2
Dynamic: license-file
